wiggle_sensors/__init__.py
wiggle_sensors/accelerometer.py
wiggle_sensors/environment.py
wiggle_sensors/gate.py
wiggle_sensors/hourly.py
wiggle_sensors/main.py
wiggle_sensors/soil_moisture.py
wiggle_sensors/soil_temperature.py
wiggle_sensors/write.py
wiggle_sensors-0.0.2.dist-info/METADATA
wiggle_sensors-0.0.2.dist-info/WHEEL
wiggle_sensors-0.0.2.dist-info/entry_points.txt
wiggle_sensors-0.0.2.dist-info/top_level.txt
wiggle_sensors-0.0.2.dist-info/RECORD
