Metadata-Version: 2.2
Name: wiggle_sensors
Version: 0.0.2
Summary: WiggleSensors - Track sensor data like temperature, gas, pressure and humidity
Author: Studio Rabota
Project-URL: Homepage, https://github.com/wiggle-bin/wiggle-sensors.git
Classifier: Programming Language :: Python :: 3
Classifier: Operating System :: OS Independent
Requires-Python: >=3.7
Requires-Dist: adafruit-circuitpython-bme680
Requires-Dist: adafruit-circuitpython-adxl34x
Requires-Dist: adafruit-circuitpython-ads1x15
Requires-Dist: gpiozero
